{"title":"WoodmanCastingX - Casting of Emy Russo.mp4","uid":8228617,"size":1244888466,"categoryP":"porn","categoryS":"movie_clips","magnet":"?xt=urn:btih:11c952498ab15db0db8678399d41b862e40f8383&amp;dn=WoodmanCastingX+-+Casting+of+Emy+Russo.mp4&amp;tr=udp%3A%2F%2Ftracker.openbittorrent.com%3A80&amp;tr=udp%3A%2F%2Fopen.demonii.com%3A1337&amp;tr=udp%3A%2F%2Ftracker.coppersurfer.tk%3A6969&amp;tr=udp%3A%2F%2Fexodus.desync.com%3A6969","seeders":0,"leechers":2,"uploader":"1.No.1","files":-1,"time":1362674641,"description":"WoodmanCastingX - Casting of Emy Russo.mp4\n\n2012, Anal, Rough Sex, Hardcore, Spanking, Rimming, Analingus, Casting, XXX, Adult\n\n960 x 540\n\n01:49:18\n\n1.16 GB\n\nScreens\n &lt;a href=&quot;\nhttp://www.pixsor.com/share-EBDE_5138BA8E.html&quot; rel=&quot;nofollow&quot; target=&quot;_NEW&quot;&gt;\nhttp://www.pixsor.com/share-EBDE_5138BA8E.html&lt;/a&gt;\n &lt;a href=&quot;\nhttp://www.pixsor.com/share-9CCC_5138BA8E.html&quot; rel=&quot;nofollow&quot; target=&quot;_NEW&quot;&gt;\nhttp://www.pixsor.com/share-9CCC_5138BA8E.html&lt;/a&gt;","torrent":{"xt":"urn:btih:11c952498ab15db0db8678399d41b862e40f8383","amp;dn":"WoodmanCastingX+-+Casting+of+Emy+Russo.mp4","amp;tr":["udp%3A%2F%2Ftracker.openbittorrent.com%3A80","udp%3A%2F%2Fopen.demonii.com%3A1337","udp%3A%2F%2Ftracker.coppersurfer.tk%3A6969","udp%3A%2F%2Fexodus.desync.com%3A6969"],"infoHash":"11c952498ab15db0db8678399d41b862e40f8383","infoHashBuffer":{"type":"Buffer","data":[17,201,82,73,138,177,93,176,219,134,120,57,157,65,184,98,228,15,131,131]},"announce":[],"urlList":[]}}