{"title":"UTO_Alpha3_PC.zip","uid":8046239,"size":151257625,"categoryP":"games","categoryS":"pc","magnet":"?xt=urn:btih:1906cde5e7ab05ffe37cc8529175881d668a058b&amp;dn=UTO_Alpha3_PC.zip&amp;tr=udp%3A%2F%2Ftracker.openbittorrent.com%3A80&amp;tr=udp%3A%2F%2Fopen.demonii.com%3A1337&amp;tr=udp%3A%2F%2Ftracker.coppersurfer.tk%3A6969&amp;tr=udp%3A%2F%2Fexodus.desync.com%3A6969","seeders":0,"leechers":0,"uploader":"Rednaxx3","files":1,"time":1358752402,"description":"Under The Ocean Alpha 3. Gem of a game. :)","torrent":{"xt":"urn:btih:1906cde5e7ab05ffe37cc8529175881d668a058b","amp;dn":"UTO_Alpha3_PC.zip","amp;tr":["udp%3A%2F%2Ftracker.openbittorrent.com%3A80","udp%3A%2F%2Fopen.demonii.com%3A1337","udp%3A%2F%2Ftracker.coppersurfer.tk%3A6969","udp%3A%2F%2Fexodus.desync.com%3A6969"],"infoHash":"1906cde5e7ab05ffe37cc8529175881d668a058b","infoHashBuffer":{"type":"Buffer","data":[25,6,205,229,231,171,5,255,227,124,200,82,145,117,136,29,102,138,5,139]},"announce":[],"urlList":[]}}