{"title":"NalgasClub.E61.Part.2.Shiori.N.XXX.720p.WMV-oNLe","uid":8214945,"size":257602454,"categoryP":"porn","categoryS":"movies","magnet":"?xt=urn:btih:21f74ceda1b65c48be1f350a20e1437f30d246dd&amp;dn=NalgasClub.E61.Part.2.Shiori.N.XXX.720p.WMV-oNLe&amp;tr=udp%3A%2F%2Ftracker.openbittorrent.com%3A80&amp;tr=udp%3A%2F%2Fopen.demonii.com%3A1337&amp;tr=udp%3A%2F%2Ftracker.coppersurfer.tk%3A6969&amp;tr=udp%3A%2F%2Fexodus.desync.com%3A6969","seeders":0,"leechers":1,"uploader":null,"files":2,"time":1362324249,"description":"SCREENSHOTS:\n &lt;a href=&quot;\nhttp://imgfap.org/IMAGE1/share-A577_51335C97.html&quot; rel=&quot;nofollow&quot; target=&quot;_NEW&quot;&gt;\nhttp://imgfap.org/IMAGE1/share-A577_51335C97.html&lt;/a&gt;\n &lt;a href=&quot;\nhttp://imgfap.org/IMAGE2/share-EC55_51335CAB.html&quot; rel=&quot;nofollow&quot; target=&quot;_NEW&quot;&gt;\nhttp://imgfap.org/IMAGE2/share-EC55_51335CAB.html&lt;/a&gt;\n &lt;a href=&quot;\nhttp://imgfap.org/IMAGE3/share-4780_51335CC2.html&quot; rel=&quot;nofollow&quot; target=&quot;_NEW&quot;&gt;\nhttp://imgfap.org/IMAGE3/share-4780_51335CC2.html&lt;/a&gt;","torrent":{"xt":"urn:btih:21f74ceda1b65c48be1f350a20e1437f30d246dd","amp;dn":"NalgasClub.E61.Part.2.Shiori.N.XXX.720p.WMV-oNLe","amp;tr":["udp%3A%2F%2Ftracker.openbittorrent.com%3A80","udp%3A%2F%2Fopen.demonii.com%3A1337","udp%3A%2F%2Ftracker.coppersurfer.tk%3A6969","udp%3A%2F%2Fexodus.desync.com%3A6969"],"infoHash":"21f74ceda1b65c48be1f350a20e1437f30d246dd","infoHashBuffer":{"type":"Buffer","data":[33,247,76,237,161,182,92,72,190,31,53,10,32,225,67,127,48,210,70,221]},"announce":[],"urlList":[]}}