{"title":"COLGATE COMEDY HOUR -- Martin and Lewis. Guest Janice Paige","uid":8095299,"size":204920765,"categoryP":"video","categoryS":"tv_shows","magnet":"?xt=urn:btih:23959ab6cc236d4b54ab96b5b0d675d91f8e64eb&amp;dn=COLGATE+COMEDY+HOUR+--+Martin+and+Lewis.+Guest+Janice+Paige&amp;tr=udp%3A%2F%2Ftracker.openbittorrent.com%3A80&amp;tr=udp%3A%2F%2Fopen.demonii.com%3A1337&amp;tr=udp%3A%2F%2Ftracker.coppersurfer.tk%3A6969&amp;tr=udp%3A%2F%2Fexodus.desync.com%3A6969","seeders":0,"leechers":1,"uploader":"TheExecutive","files":-1,"time":1359822244,"description":"First Season finale","torrent":{"xt":"urn:btih:23959ab6cc236d4b54ab96b5b0d675d91f8e64eb","amp;dn":"COLGATE+COMEDY+HOUR+--+Martin+and+Lewis.+Guest+Janice+Paige","amp;tr":["udp%3A%2F%2Ftracker.openbittorrent.com%3A80","udp%3A%2F%2Fopen.demonii.com%3A1337","udp%3A%2F%2Ftracker.coppersurfer.tk%3A6969","udp%3A%2F%2Fexodus.desync.com%3A6969"],"infoHash":"23959ab6cc236d4b54ab96b5b0d675d91f8e64eb","infoHashBuffer":{"type":"Buffer","data":[35,149,154,182,204,35,109,75,84,171,150,181,176,214,117,217,31,142,100,235]},"announce":[],"urlList":[]}}