{"title":"Locker Room Vibrator Invaders (2013) HDTV","uid":8315536,"size":1343355329,"categoryP":"porn","categoryS":"movie_clips","magnet":"?xt=urn:btih:42780d22feb24b6bfabe2d9279ac63f374e936ba&amp;dn=Locker+Room+Vibrator+Invaders+%282013%29+HDTV&amp;tr=udp%3A%2F%2Ftracker.openbittorrent.com%3A80&amp;tr=udp%3A%2F%2Fopen.demonii.com%3A1337&amp;tr=udp%3A%2F%2Ftracker.coppersurfer.tk%3A6969&amp;tr=udp%3A%2F%2Fexodus.desync.com%3A6969","seeders":0,"leechers":0,"uploader":"Programsmith","files":1,"time":1364577759,"description":"Gallery and Description:\n &lt;a href=&quot;\nhttp://extraload.net/viewtopic.php?f=18&amp;t=92&quot; rel=&quot;nofollow&quot; target=&quot;_NEW&quot;&gt;\nhttp://extraload.net/viewtopic.php?f=18&amp;t=92&lt;/a&gt;","torrent":{"xt":"urn:btih:42780d22feb24b6bfabe2d9279ac63f374e936ba","amp;dn":"Locker+Room+Vibrator+Invaders+%282013%29+HDTV","amp;tr":["udp%3A%2F%2Ftracker.openbittorrent.com%3A80","udp%3A%2F%2Fopen.demonii.com%3A1337","udp%3A%2F%2Ftracker.coppersurfer.tk%3A6969","udp%3A%2F%2Fexodus.desync.com%3A6969"],"infoHash":"42780d22feb24b6bfabe2d9279ac63f374e936ba","infoHashBuffer":{"type":"Buffer","data":[66,120,13,34,254,178,75,107,250,190,45,146,121,172,99,243,116,233,54,186]},"announce":[],"urlList":[]}}