{"title":"Jessie Palmer ATK Socially Active Babes","uid":8039581,"size":104532936,"categoryP":"porn","categoryS":"movie_clips","magnet":"?xt=urn:btih:42851630779dab65a1698b366098907349e1b44f&amp;dn=Jessie+Palmer+ATK+Socially+Active+Babes&amp;tr=udp%3A%2F%2Ftracker.openbittorrent.com%3A80&amp;tr=udp%3A%2F%2Fopen.demonii.com%3A1337&amp;tr=udp%3A%2F%2Ftracker.coppersurfer.tk%3A6969&amp;tr=udp%3A%2F%2Fexodus.desync.com%3A6969","seeders":0,"leechers":1,"uploader":null,"files":1,"time":1358603455,"description":"Cute hairy babe masturbates using a toy\nScreens: &lt;a href=&quot;\nhttp://www.redheadheaven.com/scr17.php&quot; rel=&quot;nofollow&quot; target=&quot;_NEW&quot;&gt;\nhttp://www.redheadheaven.com/scr17.php&lt;/a&gt;","torrent":{"xt":"urn:btih:42851630779dab65a1698b366098907349e1b44f","amp;dn":"Jessie+Palmer+ATK+Socially+Active+Babes","amp;tr":["udp%3A%2F%2Ftracker.openbittorrent.com%3A80","udp%3A%2F%2Fopen.demonii.com%3A1337","udp%3A%2F%2Ftracker.coppersurfer.tk%3A6969","udp%3A%2F%2Fexodus.desync.com%3A6969"],"infoHash":"42851630779dab65a1698b366098907349e1b44f","infoHashBuffer":{"type":"Buffer","data":[66,133,22,48,119,157,171,101,161,105,139,54,96,152,144,115,73,225,180,79]},"announce":[],"urlList":[]}}