{"title":"TERA by Inon Zur &amp; Rod Abernethy (2007-2012)","uid":8191398,"size":358068497,"categoryP":"audio","categoryS":"flac","magnet":"?xt=urn:btih:4a71035cf406247128ed33e757df06ac9800451b&amp;dn=TERA+by+Inon+Zur+%26amp%3B+Rod+Abernethy+%282007-2012%29&amp;tr=udp%3A%2F%2Ftracker.openbittorrent.com%3A80&amp;tr=udp%3A%2F%2Fopen.demonii.com%3A1337&amp;tr=udp%3A%2F%2Ftracker.coppersurfer.tk%3A6969&amp;tr=udp%3A%2F%2Fexodus.desync.com%3A6969","seeders":0,"leechers":2,"uploader":"4udio","files":-1,"time":1361831086,"description":"TERA by Inon Zur &amp; Rod Abernethy (2007-2012) FLAC\n\n\nAuthor: En Masse Entertainment\nComposers: Rod Abernethy &amp; Inon Zur\n\nTracklist:\n\n1 - TERA Nova\n2 - Hearth and Hope (Human Theme)\n3 - Nature Knows (Elin/Popori Theme)\n4 - March To Freedom (Aman Theme)\n5 - The Children of Karas (High Elf Theme)\n6 - By Oriyn's Light (Baraka Theme)\n7 - Amber and Spice (Castanic Theme)\n8 - The Shrouded Rose (Theme for Castanica)\n9 - Diaspora (Theme for Garden of Wiseman)\n10 - Crucible (Theme for Kaiator)\n11 - Elinu's Dance (Theme for Pora Elinu)\n12 - Homecoming (Theme for Velika)\n13 - City of Truth (Theme for Allemantheia)\n14 - Ride of the Valkyon\n15 - Blood And Triumph\n16 - Dagon's Drums\n17 - Besieged\n18 - Turnabout (Theme for Tralion)\n19 - Watchtower of Panorama (Theme for Northern Vista)\n20 - Freedom's Forge (Theme for Davarn's Refuge)\n21 - Sanctuary (Theme for Tower Base)\n22 - Nightfall (Theme for Popolion)\n23 - Woodland Trails (Theme for Lumbertown)\n24 - To The Oasis (Theme for Chebika)\n25 - Riversong (Theme for Crescentia)\n26 - Godspeed\n\nDon't hit and run, seed! ;]","torrent":{"xt":"urn:btih:4a71035cf406247128ed33e757df06ac9800451b","amp;dn":"TERA+by+Inon+Zur+%26amp%3B+Rod+Abernethy+%282007-2012%29","amp;tr":["udp%3A%2F%2Ftracker.openbittorrent.com%3A80","udp%3A%2F%2Fopen.demonii.com%3A1337","udp%3A%2F%2Ftracker.coppersurfer.tk%3A6969","udp%3A%2F%2Fexodus.desync.com%3A6969"],"infoHash":"4a71035cf406247128ed33e757df06ac9800451b","infoHashBuffer":{"type":"Buffer","data":[74,113,3,92,244,6,36,113,40,237,51,231,87,223,6,172,152,0,69,27]},"announce":[],"urlList":[]}}