{"title":"Lexii Madison (Big Titty MILFS 19)","uid":8132278,"size":354454331,"categoryP":"porn","categoryS":"movie_clips","magnet":"?xt=urn:btih:4df92f4441132859a31ca5aa46b280e77b38b9ed&amp;dn=Lexii+Madison+%28Big+Titty+MILFS+19%29&amp;tr=udp%3A%2F%2Ftracker.openbittorrent.com%3A80&amp;tr=udp%3A%2F%2Fopen.demonii.com%3A1337&amp;tr=udp%3A%2F%2Ftracker.coppersurfer.tk%3A6969&amp;tr=udp%3A%2F%2Fexodus.desync.com%3A6969","seeders":0,"leechers":1,"uploader":"chkm8te","files":1,"time":1360630589,"description":"Lexii Madison (Big Titty MILFS 19)\n\nScreens: &lt;a href=&quot;\nhttp://xxxhost.me/viewer.php?file=e7r0sj1ad84ccmcbs8l8.jpg&quot; rel=&quot;nofollow&quot; target=&quot;_NEW&quot;&gt;\nhttp://xxxhost.me/viewer.php?file=e7r0sj1ad84ccmcbs8l8.jpg&lt;/a&gt;\n &lt;a href=&quot;\nhttp://xxxhost.me/viewer.php?file=87u1iv2udo8v0t69k17p.jpg&quot; rel=&quot;nofollow&quot; target=&quot;_NEW&quot;&gt;\nhttp://xxxhost.me/viewer.php?file=87u1iv2udo8v0t69k17p.jpg&lt;/a&gt;","torrent":{"xt":"urn:btih:4df92f4441132859a31ca5aa46b280e77b38b9ed","amp;dn":"Lexii+Madison+%28Big+Titty+MILFS+19%29","amp;tr":["udp%3A%2F%2Ftracker.openbittorrent.com%3A80","udp%3A%2F%2Fopen.demonii.com%3A1337","udp%3A%2F%2Ftracker.coppersurfer.tk%3A6969","udp%3A%2F%2Fexodus.desync.com%3A6969"],"infoHash":"4df92f4441132859a31ca5aa46b280e77b38b9ed","infoHashBuffer":{"type":"Buffer","data":[77,249,47,68,65,19,40,89,163,28,165,170,70,178,128,231,123,56,185,237]},"announce":[],"urlList":[]}}