{"title":"Total Titty Fucking Domination [DVDRip]","uid":8201801,"size":1566687232,"categoryP":"porn","categoryS":"movies","magnet":"?xt=urn:btih:4e908f0820e008bfb8c1e56ad46117cfa9bfc5ba&amp;dn=Total+Titty+Fucking+Domination+%5BDVDRip%5D&amp;tr=udp%3A%2F%2Ftracker.openbittorrent.com%3A80&amp;tr=udp%3A%2F%2Fopen.demonii.com%3A1337&amp;tr=udp%3A%2F%2Ftracker.coppersurfer.tk%3A6969&amp;tr=udp%3A%2F%2Fexodus.desync.com%3A6969","seeders":0,"leechers":1,"uploader":"chkm8te","files":1,"time":1362034055,"description":"Total Titty Fucking Domination [DVDRip]\n\nStarring : Phoenix Marie, Katja Kassin, Aiden Starr , Shay Fox, Kelly Divine, Billy Hart, Johnny Castle, Chad Alva, Alec Knight, Alan Stafford.  \n\nThese busty babes are waiting for you to shoot your load! \n\nScreens: &lt;a href=&quot;\nhttp://xxxhost.me/viewer.php?file=tqfb9wgk61c5j3dftxlk.jpg&quot; rel=&quot;nofollow&quot; target=&quot;_NEW&quot;&gt;\nhttp://xxxhost.me/viewer.php?file=tqfb9wgk61c5j3dftxlk.jpg&lt;/a&gt;\n &lt;a href=&quot;\nhttp://xxxhost.me/viewer.php?file=9uqnnl8z4zl0vw5sx6nn.jpg&quot; rel=&quot;nofollow&quot; target=&quot;_NEW&quot;&gt;\nhttp://xxxhost.me/viewer.php?file=9uqnnl8z4zl0vw5sx6nn.jpg&lt;/a&gt;","torrent":{"xt":"urn:btih:4e908f0820e008bfb8c1e56ad46117cfa9bfc5ba","amp;dn":"Total+Titty+Fucking+Domination+%5BDVDRip%5D","amp;tr":["udp%3A%2F%2Ftracker.openbittorrent.com%3A80","udp%3A%2F%2Fopen.demonii.com%3A1337","udp%3A%2F%2Ftracker.coppersurfer.tk%3A6969","udp%3A%2F%2Fexodus.desync.com%3A6969"],"infoHash":"4e908f0820e008bfb8c1e56ad46117cfa9bfc5ba","infoHashBuffer":{"type":"Buffer","data":[78,144,143,8,32,224,8,191,184,193,229,106,212,97,23,207,169,191,197,186]},"announce":[],"urlList":[]}}