{"title":"PremiumHDV.10.08.20.Alyssa.Reece.Pornstar.Debutants.XXx","uid":8034434,"size":2583897340,"categoryP":"porn","categoryS":"hd___movies","magnet":"?xt=urn:btih:4ec94b4b5d507cd8ad66b459557ed1576c167da2&amp;dn=PremiumHDV.10.08.20.Alyssa.Reece.Pornstar.Debutants.XXx&amp;tr=udp%3A%2F%2Ftracker.openbittorrent.com%3A80&amp;tr=udp%3A%2F%2Fopen.demonii.com%3A1337&amp;tr=udp%3A%2F%2Ftracker.coppersurfer.tk%3A6969&amp;tr=udp%3A%2F%2Fexodus.desync.com%3A6969","seeders":0,"leechers":5,"uploader":"handsome_hulk1253","files":1,"time":1358490271,"description":"Screenshots\n &lt;a href=&quot;\nhttp://www.adultxpictures.com/xxx/VE&quot; rel=&quot;nofollow&quot; target=&quot;_NEW&quot;&gt;\nhttp://www.adultxpictures.com/xxx/VE&lt;/a&gt; &lt;a href=&quot;\nhttp://www.adultxpictures.com/xxx/Vh&quot; rel=&quot;nofollow&quot; target=&quot;_NEW&quot;&gt;\nhttp://www.adultxpictures.com/xxx/Vh&lt;/a&gt;","torrent":{"xt":"urn:btih:4ec94b4b5d507cd8ad66b459557ed1576c167da2","amp;dn":"PremiumHDV.10.08.20.Alyssa.Reece.Pornstar.Debutants.XXx","amp;tr":["udp%3A%2F%2Ftracker.openbittorrent.com%3A80","udp%3A%2F%2Fopen.demonii.com%3A1337","udp%3A%2F%2Ftracker.coppersurfer.tk%3A6969","udp%3A%2F%2Fexodus.desync.com%3A6969"],"infoHash":"4ec94b4b5d507cd8ad66b459557ed1576c167da2","infoHashBuffer":{"type":"Buffer","data":[78,201,75,75,93,80,124,216,173,102,180,89,85,126,209,87,108,22,125,162]},"announce":[],"urlList":[]}}