{"title":"[EvilAngel] Mira Sunset (Christophs Anal Attraction / 01.21.2013","uid":8049559,"size":1613171805,"categoryP":"porn","categoryS":"hd___movies","magnet":"?xt=urn:btih:59c90ec138be1472a9533ec05522820ee218e89a&amp;dn=%5BEvilAngel%5D+Mira+Sunset+%28Christophs+Anal+Attraction+%2F+01.21.2013&amp;tr=udp%3A%2F%2Ftracker.openbittorrent.com%3A80&amp;tr=udp%3A%2F%2Fopen.demonii.com%3A1337&amp;tr=udp%3A%2F%2Ftracker.coppersurfer.tk%3A6969&amp;tr=udp%3A%2F%2Fexodus.desync.com%3A6969","seeders":0,"leechers":1,"uploader":"chkm8te","files":1,"time":1358828053,"description":"[EvilAngel] Mira Sunset (Christophs Anal Attraction / 01.21.2013)\nres:720p\n\nScreens:  &lt;a href=&quot;\nhttp://xxxhost.me/viewer.php?file=1vqyd55vybtg0lladwkh.jpg&quot; rel=&quot;nofollow&quot; target=&quot;_NEW&quot;&gt;\nhttp://xxxhost.me/viewer.php?file=1vqyd55vybtg0lladwkh.jpg&lt;/a&gt;\n  &lt;a href=&quot;\nhttp://xxxhost.me/viewer.php?file=fp5xf1l24ykhs3izumjv.jpg&quot; rel=&quot;nofollow&quot; target=&quot;_NEW&quot;&gt;\nhttp://xxxhost.me/viewer.php?file=fp5xf1l24ykhs3izumjv.jpg&lt;/a&gt;","torrent":{"xt":"urn:btih:59c90ec138be1472a9533ec05522820ee218e89a","amp;dn":"%5BEvilAngel%5D+Mira+Sunset+%28Christophs+Anal+Attraction+%2F+01.21.2013","amp;tr":["udp%3A%2F%2Ftracker.openbittorrent.com%3A80","udp%3A%2F%2Fopen.demonii.com%3A1337","udp%3A%2F%2Ftracker.coppersurfer.tk%3A6969","udp%3A%2F%2Fexodus.desync.com%3A6969"],"infoHash":"59c90ec138be1472a9533ec05522820ee218e89a","infoHashBuffer":{"type":"Buffer","data":[89,201,14,193,56,190,20,114,169,83,62,192,85,34,130,14,226,24,232,154]},"announce":[],"urlList":[]}}