{"title":"Lexi Swallow - Relax The Pussy! (Pornstar Spa)","uid":8004894,"size":443075581,"categoryP":"porn","categoryS":"movie_clips","magnet":"?xt=urn:btih:5e74b611b3108f4ec9912c1eee3fa56a63dbe5e8&amp;dn=Lexi+Swallow+-+Relax+The+Pussy%21+%28Pornstar+Spa%29&amp;tr=udp%3A%2F%2Ftracker.openbittorrent.com%3A80&amp;tr=udp%3A%2F%2Fopen.demonii.com%3A1337&amp;tr=udp%3A%2F%2Ftracker.coppersurfer.tk%3A6969&amp;tr=udp%3A%2F%2Fexodus.desync.com%3A6969","seeders":0,"leechers":1,"uploader":"R0thschild","files":1,"time":1357865417,"description":"Gallery: \n &lt;a href=&quot;\nhttp://hqpdb.com/viewtopic.php?f=11&amp;t=7840&quot; rel=&quot;nofollow&quot; target=&quot;_NEW&quot;&gt;\nhttp://hqpdb.com/viewtopic.php?f=11&amp;t=7840&lt;/a&gt;","torrent":{"xt":"urn:btih:5e74b611b3108f4ec9912c1eee3fa56a63dbe5e8","amp;dn":"Lexi+Swallow+-+Relax+The+Pussy%21+%28Pornstar+Spa%29","amp;tr":["udp%3A%2F%2Ftracker.openbittorrent.com%3A80","udp%3A%2F%2Fopen.demonii.com%3A1337","udp%3A%2F%2Ftracker.coppersurfer.tk%3A6969","udp%3A%2F%2Fexodus.desync.com%3A6969"],"infoHash":"5e74b611b3108f4ec9912c1eee3fa56a63dbe5e8","infoHashBuffer":{"type":"Buffer","data":[94,116,182,17,179,16,143,78,201,145,44,30,238,63,165,106,99,219,229,232]},"announce":[],"urlList":[]}}