{"title":"Dont Tell My Husband 2 XXX DVDRip x264-Pr0nStarS","uid":8159038,"size":939284801,"categoryP":"porn","categoryS":"movies","magnet":"?xt=urn:btih:665404d0f1f000f2949a9c2fab1fb769a87298c6&amp;dn=Dont+Tell+My+Husband+2+XXX+DVDRip+x264-Pr0nStarS&amp;tr=udp%3A%2F%2Ftracker.openbittorrent.com%3A80&amp;tr=udp%3A%2F%2Fopen.demonii.com%3A1337&amp;tr=udp%3A%2F%2Ftracker.coppersurfer.tk%3A6969&amp;tr=udp%3A%2F%2Fexodus.desync.com%3A6969","seeders":0,"leechers":1,"uploader":"xxxlavalxxx","files":1,"time":1361212929,"description":"\nStarring\nMaya Hills, Samantha Ryan, Cece Stone, Mark Wood, James Deen, Derrick Pierce, Anthony Rosano, Jayden Jaymes, Tommy Pistol, Ashli Ames\nGenre\nAll Sex, MILF\nDescription\nDon't Tell My Husband # 2 porn Starring Jayden Jaymes! Every MILF Has A Young Secret!Your favorite cheating housewife whores are back and they're horny as hell! It's no secret that these hottie MILFs crave more hardcore action than their husbands can deliver, so keep your mouth shut and your cock hard cuz he could be home any minute! Being unfaithful feels so fucking good!\n\n &lt;a href=&quot;\nhttp://www.forload.net/?v=fcoc.jpg&quot; rel=&quot;nofollow&quot; target=&quot;_NEW&quot;&gt;\nhttp://www.forload.net/?v=fcoc.jpg&lt;/a&gt;\n &lt;a href=&quot;\nhttp://www.forload.net/?v=bmkm.jpg&quot; rel=&quot;nofollow&quot; target=&quot;_NEW&quot;&gt;\nhttp://www.forload.net/?v=bmkm.jpg&lt;/a&gt;\n &lt;a href=&quot;\nhttp://www.forload.net/?v=psdtmyh2mp.jpg&quot; rel=&quot;nofollow&quot; target=&quot;_NEW&quot;&gt;\nhttp://www.forload.net/?v=psdtmyh2mp.jpg&lt;/a&gt;","torrent":{"xt":"urn:btih:665404d0f1f000f2949a9c2fab1fb769a87298c6","amp;dn":"Dont+Tell+My+Husband+2+XXX+DVDRip+x264-Pr0nStarS","amp;tr":["udp%3A%2F%2Ftracker.openbittorrent.com%3A80","udp%3A%2F%2Fopen.demonii.com%3A1337","udp%3A%2F%2Ftracker.coppersurfer.tk%3A6969","udp%3A%2F%2Fexodus.desync.com%3A6969"],"infoHash":"665404d0f1f000f2949a9c2fab1fb769a87298c6","infoHashBuffer":{"type":"Buffer","data":[102,84,4,208,241,240,0,242,148,154,156,47,171,31,183,105,168,114,152,198]},"announce":[],"urlList":[]}}