{"title":"Offender.2012.BDRip.x264-SONiDO","uid":7967893,"size":749101811,"categoryP":"video","categoryS":"movies","magnet":"?xt=urn:btih:6bdd898012d4416ac5ba8df1a7817d68f73b1e0c&amp;dn=Offender.2012.BDRip.x264-SONiDO&amp;tr=udp%3A%2F%2Ftracker.openbittorrent.com%3A80&amp;tr=udp%3A%2F%2Fopen.demonii.com%3A1337&amp;tr=udp%3A%2F%2Ftracker.coppersurfer.tk%3A6969&amp;tr=udp%3A%2F%2Fexodus.desync.com%3A6969","seeders":0,"leechers":0,"uploader":"TvTeam","files":6,"time":1356730894,"description":"::::::::::::::::::::::::::::::::::::::::::::::::::::::::::::::::::::::::::\n  &lt;a href=&quot;\nhttp://www.torrenting.com&quot; rel=&quot;nofollow&quot; target=&quot;_NEW&quot;&gt;\nhttp://www.torrenting.com&lt;/a&gt;  : TOP MOVIE TORRENT SITE -  Sign up is OPEN for now!\n\n::::::::::::::::::::::::::::::::::::::::::::::::::::::::::::::::::::::::::\n\n(((((((((((((= Enjoy No RAR releases =))))))))))))))))))))\n\n\n...................................NFO:....................................\n\nEnjoy our Fast Upload.\nFor more info about this release, open .NFO file with notepad !!!\n\n-------------------------------------------------------------------------------------\n\n\nMust Try:  &lt;a href=&quot; http://www.torrenting.com&quot; rel=&quot;nofollow&quot; target=&quot;_NEW&quot;&gt; http://www.torrenting.com&lt;/a&gt;\n\nVisit it, Sit back, enjoy. I am sure you'll like it.","torrent":{"xt":"urn:btih:6bdd898012d4416ac5ba8df1a7817d68f73b1e0c","amp;dn":"Offender.2012.BDRip.x264-SONiDO","amp;tr":["udp%3A%2F%2Ftracker.openbittorrent.com%3A80","udp%3A%2F%2Fopen.demonii.com%3A1337","udp%3A%2F%2Ftracker.coppersurfer.tk%3A6969","udp%3A%2F%2Fexodus.desync.com%3A6969"],"infoHash":"6bdd898012d4416ac5ba8df1a7817d68f73b1e0c","infoHashBuffer":{"type":"Buffer","data":[107,221,137,128,18,212,65,106,197,186,141,241,167,129,125,104,247,59,30,12]},"announce":[],"urlList":[]}}