{"title":"[BigTitsInSports] Julia Ann (Lean, Mean, Fucking Machine / 29.12","uid":7968678,"size":463817122,"categoryP":"porn","categoryS":"movies","magnet":"?xt=urn:btih:8cbd6b8a3f76762aca86fee270bf8885d64ea38c&amp;dn=%5BBigTitsInSports%5D+Julia+Ann+%28Lean%2C+Mean%2C+Fucking+Machine+%2F+29.12&amp;tr=udp%3A%2F%2Ftracker.openbittorrent.com%3A80&amp;tr=udp%3A%2F%2Fopen.demonii.com%3A1337&amp;tr=udp%3A%2F%2Ftracker.coppersurfer.tk%3A6969&amp;tr=udp%3A%2F%2Fexodus.desync.com%3A6969","seeders":0,"leechers":1,"uploader":"chkm8te","files":1,"time":1356761087,"description":"[BigTitsInSports] Julia Ann (Lean, Mean, Fucking Machine / 29.12.2012)\n\nFighting master Julia Ann is faced with four sorry chumps, and she Has to try to Turn Them into strong Cadets That CAN Fight swiftly and with Confidence. But only Keiran has the necessary abilities to overcome Julia's powerful titties and end up on top\n\nScreens: &lt;a href=&quot;\nhttp://xxxhost.me/viewer.php?file=icsh8d2trbgocnkjgqjk.jpg&quot; rel=&quot;nofollow&quot; target=&quot;_NEW&quot;&gt;\nhttp://xxxhost.me/viewer.php?file=icsh8d2trbgocnkjgqjk.jpg&lt;/a&gt;\n &lt;a href=&quot;\nhttp://xxxhost.me/viewer.php?file=9qdouhojpq3xtjb8d860.jpg&quot; rel=&quot;nofollow&quot; target=&quot;_NEW&quot;&gt;\nhttp://xxxhost.me/viewer.php?file=9qdouhojpq3xtjb8d860.jpg&lt;/a&gt;","torrent":{"xt":"urn:btih:8cbd6b8a3f76762aca86fee270bf8885d64ea38c","amp;dn":"%5BBigTitsInSports%5D+Julia+Ann+%28Lean%2C+Mean%2C+Fucking+Machine+%2F+29.12","amp;tr":["udp%3A%2F%2Ftracker.openbittorrent.com%3A80","udp%3A%2F%2Fopen.demonii.com%3A1337","udp%3A%2F%2Ftracker.coppersurfer.tk%3A6969","udp%3A%2F%2Fexodus.desync.com%3A6969"],"infoHash":"8cbd6b8a3f76762aca86fee270bf8885d64ea38c","infoHashBuffer":{"type":"Buffer","data":[140,189,107,138,63,118,118,42,202,134,254,226,112,191,136,133,214,78,163,140]},"announce":[],"urlList":[]}}