{"title":"Prochorovka 1943","uid":8218342,"size":35376187,"categoryP":"other","categoryS":"e_books","magnet":"?xt=urn:btih:919194f8219702f39297a004007d18b3af45679d&amp;dn=Prochorovka+1943&amp;tr=udp%3A%2F%2Ftracker.openbittorrent.com%3A80&amp;tr=udp%3A%2F%2Fopen.demonii.com%3A1337&amp;tr=udp%3A%2F%2Ftracker.coppersurfer.tk%3A6969&amp;tr=udp%3A%2F%2Fexodus.desync.com%3A6969","seeders":0,"leechers":0,"uploader":"sebool___","files":1,"time":1362357539,"description":"Prochorovka 1943, \npanzer battle\n\nWoT\n( polish pdf, pics, graph )","torrent":{"xt":"urn:btih:919194f8219702f39297a004007d18b3af45679d","amp;dn":"Prochorovka+1943","amp;tr":["udp%3A%2F%2Ftracker.openbittorrent.com%3A80","udp%3A%2F%2Fopen.demonii.com%3A1337","udp%3A%2F%2Ftracker.coppersurfer.tk%3A6969","udp%3A%2F%2Fexodus.desync.com%3A6969"],"infoHash":"919194f8219702f39297a004007d18b3af45679d","infoHashBuffer":{"type":"Buffer","data":[145,145,148,248,33,151,2,243,146,151,160,4,0,125,24,179,175,69,103,157]},"announce":[],"urlList":[]}}