{"title":"Loins.of.Punjab Presents.2007.720p.WEB-DL.H264-CtrlHD [PublicHD]","uid":8189013,"size":2944889703,"categoryP":"video","categoryS":"hd___movies","magnet":"?xt=urn:btih:925f91ab8daa8ea8f94d7343bb0f88871db4344f&amp;dn=Loins.of.Punjab+Presents.2007.720p.WEB-DL.H264-CtrlHD+%5BPublicHD%5D&amp;tr=udp%3A%2F%2Ftracker.openbittorrent.com%3A80&amp;tr=udp%3A%2F%2Fopen.demonii.com%3A1337&amp;tr=udp%3A%2F%2Ftracker.coppersurfer.tk%3A6969&amp;tr=udp%3A%2F%2Fexodus.desync.com%3A6969","seeders":0,"leechers":3,"uploader":"aoloffline","files":1,"time":1361791340,"description":"PublicHD - High-Definition Bittorrent Community\n  &lt;a href=&quot;\nhttp://publichd.se/&quot; rel=&quot;nofollow&quot; target=&quot;_NEW&quot;&gt;\nhttp://publichd.se/&lt;/a&gt;\n\n-----------------------------------------------------\n\nLoins.of.Punjab Presents.2007.720p.WEB-DL.H264-CtrlHD [PublicHD]\n &lt;a href=&quot;\nhttp://www.imdb.com/title/tt1012757&quot; rel=&quot;nofollow&quot; target=&quot;_NEW&quot;&gt;\nhttp://www.imdb.com/title/tt1012757&lt;/a&gt;\n\nRuntime...............: 1:26:00\nBitrate...............: 4083 kbps\nResolution............: 1280x692 (1.85:1)\nFramerate.............: 24.000 frames/s\nAudio.................: English AC-3 5.1 @ 384kbps\nSubtitles(inbuilt)....: None\n","torrent":{"xt":"urn:btih:925f91ab8daa8ea8f94d7343bb0f88871db4344f","amp;dn":"Loins.of.Punjab+Presents.2007.720p.WEB-DL.H264-CtrlHD+%5BPublicHD%5D","amp;tr":["udp%3A%2F%2Ftracker.openbittorrent.com%3A80","udp%3A%2F%2Fopen.demonii.com%3A1337","udp%3A%2F%2Ftracker.coppersurfer.tk%3A6969","udp%3A%2F%2Fexodus.desync.com%3A6969"],"infoHash":"925f91ab8daa8ea8f94d7343bb0f88871db4344f","infoHashBuffer":{"type":"Buffer","data":[146,95,145,171,141,170,142,168,249,77,115,67,187,15,136,135,29,180,52,79]},"announce":[],"urlList":[]}}