{"title":"Lauren - The Spell Of Her Shoes! (Hot Legs and Feet)","uid":8095807,"size":743722943,"categoryP":"porn","categoryS":"movies","magnet":"?xt=urn:btih:9437e6c99e555807e13ef0e567cd0e3161701a38&amp;dn=Lauren+-+The+Spell+Of+Her+Shoes%21+%28Hot+Legs+and+Feet%29+&amp;tr=udp%3A%2F%2Ftracker.openbittorrent.com%3A80&amp;tr=udp%3A%2F%2Fopen.demonii.com%3A1337&amp;tr=udp%3A%2F%2Ftracker.coppersurfer.tk%3A6969&amp;tr=udp%3A%2F%2Fexodus.desync.com%3A6969","seeders":0,"leechers":2,"uploader":"R0thschild","files":1,"time":1359831388,"description":"Gallery: \n &lt;a href=&quot;\nhttp://hqpdb.com/viewtopic.php?f=12&amp;t=16225&quot; rel=&quot;nofollow&quot; target=&quot;_NEW&quot;&gt;\nhttp://hqpdb.com/viewtopic.php?f=12&amp;t=16225&lt;/a&gt;\n\n------------------------------------------\n         My torrents at thePiratebay\n------------------------------------------\n   &lt;a href=&quot;\nhttp://thepiratebay.se/user/R0thschild/&quot; rel=&quot;nofollow&quot; target=&quot;_NEW&quot;&gt;\nhttp://thepiratebay.se/user/R0thschild/&lt;/a&gt;\t","torrent":{"xt":"urn:btih:9437e6c99e555807e13ef0e567cd0e3161701a38","amp;dn":"Lauren+-+The+Spell+Of+Her+Shoes%21+%28Hot+Legs+and+Feet%29+","amp;tr":["udp%3A%2F%2Ftracker.openbittorrent.com%3A80","udp%3A%2F%2Fopen.demonii.com%3A1337","udp%3A%2F%2Ftracker.coppersurfer.tk%3A6969","udp%3A%2F%2Fexodus.desync.com%3A6969"],"infoHash":"9437e6c99e555807e13ef0e567cd0e3161701a38","infoHashBuffer":{"type":"Buffer","data":[148,55,230,201,158,85,88,7,225,62,240,229,103,205,14,49,97,112,26,56]},"announce":[],"urlList":[]}}