{"title":"Allysin Wonderland - Caught In The Act! (Massage-Parlor)","uid":8031923,"size":1172980503,"categoryP":"porn","categoryS":"hd___movies","magnet":"?xt=urn:btih:9d8106e70e51b62d134aa295b5fd7ed36d1d046b&amp;dn=Allysin+Wonderland+-+Caught+In+The+Act%21+%28Massage-Parlor%29&amp;tr=udp%3A%2F%2Ftracker.openbittorrent.com%3A80&amp;tr=udp%3A%2F%2Fopen.demonii.com%3A1337&amp;tr=udp%3A%2F%2Ftracker.coppersurfer.tk%3A6969&amp;tr=udp%3A%2F%2Fexodus.desync.com%3A6969","seeders":0,"leechers":1,"uploader":"R0thschild","files":1,"time":1358439035,"description":"Gallery: \n &lt;a href=&quot;\nhttp://hqpdb.com/viewtopic.php?f=12&amp;t=9864&quot; rel=&quot;nofollow&quot; target=&quot;_NEW&quot;&gt;\nhttp://hqpdb.com/viewtopic.php?f=12&amp;t=9864&lt;/a&gt;","torrent":{"xt":"urn:btih:9d8106e70e51b62d134aa295b5fd7ed36d1d046b","amp;dn":"Allysin+Wonderland+-+Caught+In+The+Act%21+%28Massage-Parlor%29","amp;tr":["udp%3A%2F%2Ftracker.openbittorrent.com%3A80","udp%3A%2F%2Fopen.demonii.com%3A1337","udp%3A%2F%2Ftracker.coppersurfer.tk%3A6969","udp%3A%2F%2Fexodus.desync.com%3A6969"],"infoHash":"9d8106e70e51b62d134aa295b5fd7ed36d1d046b","infoHashBuffer":{"type":"Buffer","data":[157,129,6,231,14,81,182,45,19,74,162,149,181,253,126,211,109,29,4,107]},"announce":[],"urlList":[]}}