{"title":"Small collection of funny gifs","uid":8073248,"size":13202743,"categoryP":"other","categoryS":"pictures","magnet":"?xt=urn:btih:a5e6ceb0a834f0e73a7ee06c9d4b15e675f17db8&amp;dn=Small+collection+of+funny+gifs+&amp;tr=udp%3A%2F%2Ftracker.openbittorrent.com%3A80&amp;tr=udp%3A%2F%2Fopen.demonii.com%3A1337&amp;tr=udp%3A%2F%2Ftracker.coppersurfer.tk%3A6969&amp;tr=udp%3A%2F%2Fexodus.desync.com%3A6969","seeders":0,"leechers":1,"uploader":"DAY07","files":13,"time":1359321909,"description":"I want to look back at this torrent 10 years from now and still see seeds (assuming tpb is still sailing which I`m sure it will :)  arrrrrrrrrrrrrr arrrrrrrrrrrrrrr ","torrent":{"xt":"urn:btih:a5e6ceb0a834f0e73a7ee06c9d4b15e675f17db8","amp;dn":"Small+collection+of+funny+gifs+","amp;tr":["udp%3A%2F%2Ftracker.openbittorrent.com%3A80","udp%3A%2F%2Fopen.demonii.com%3A1337","udp%3A%2F%2Ftracker.coppersurfer.tk%3A6969","udp%3A%2F%2Fexodus.desync.com%3A6969"],"infoHash":"a5e6ceb0a834f0e73a7ee06c9d4b15e675f17db8","infoHashBuffer":{"type":"Buffer","data":[165,230,206,176,168,52,240,231,58,126,224,108,157,75,21,230,117,241,125,184]},"announce":[],"urlList":[]}}