{"title":"ATK Aunt Judys - Alisa ali095 - 2 - 1055 pics in 6 sets","uid":8115499,"size":725636707,"categoryP":"porn","categoryS":"pictures","magnet":"?xt=urn:btih:a70b7a09d8b8018a53cc9f07b8e6aba3cee60ca3&amp;dn=ATK+Aunt+Judys+-+Alisa+ali095+-+2+-+1055+pics+in+6+sets&amp;tr=udp%3A%2F%2Ftracker.openbittorrent.com%3A80&amp;tr=udp%3A%2F%2Fopen.demonii.com%3A1337&amp;tr=udp%3A%2F%2Ftracker.coppersurfer.tk%3A6969&amp;tr=udp%3A%2F%2Fexodus.desync.com%3A6969","seeders":0,"leechers":1,"uploader":"bestec1234","files":-1,"time":1360284367,"description":" &lt;a href=&quot;http://bayimg.com/tag/ali095/&quot; rel=&quot;nofollow&quot; target=&quot;_NEW&quot;&gt;http://bayimg.com/tag/ali095/&lt;/a&gt;\n\nTo see the previews, you may have to check 'No I don't mind offensive material' under 'Settings' on bayimg.","torrent":{"xt":"urn:btih:a70b7a09d8b8018a53cc9f07b8e6aba3cee60ca3","amp;dn":"ATK+Aunt+Judys+-+Alisa+ali095+-+2+-+1055+pics+in+6+sets","amp;tr":["udp%3A%2F%2Ftracker.openbittorrent.com%3A80","udp%3A%2F%2Fopen.demonii.com%3A1337","udp%3A%2F%2Ftracker.coppersurfer.tk%3A6969","udp%3A%2F%2Fexodus.desync.com%3A6969"],"infoHash":"a70b7a09d8b8018a53cc9f07b8e6aba3cee60ca3","infoHashBuffer":{"type":"Buffer","data":[167,11,122,9,216,184,1,138,83,204,159,7,184,230,171,163,206,230,12,163]},"announce":[],"urlList":[]}}