{"title":"Deranged.2012.1080p.BluRay.DTS.x264-LooKMaNe [PublicHD]","uid":7861113,"size":8435871511,"categoryP":"video","categoryS":"hd___movies","magnet":"?xt=urn:btih:a9a11254624313a59c36b304867cb08762c7e529&amp;dn=Deranged.2012.1080p.BluRay.DTS.x264-LooKMaNe+%5BPublicHD%5D&amp;tr=udp%3A%2F%2Ftracker.openbittorrent.com%3A80&amp;tr=udp%3A%2F%2Fopen.demonii.com%3A1337&amp;tr=udp%3A%2F%2Ftracker.coppersurfer.tk%3A6969&amp;tr=udp%3A%2F%2Fexodus.desync.com%3A6969","seeders":0,"leechers":1,"uploader":"aoloffline","files":2,"time":1353891572,"description":"PublicHD - High-Definition Bittorrent Community \n    &lt;a href=&quot;\nhttp://publichd.eu/&quot; rel=&quot;nofollow&quot; target=&quot;_NEW&quot;&gt;\nhttp://publichd.eu/&lt;/a&gt;\n\n-----------------------------------------------------\n\nDeranged.2012.1080p.BluRay.DTS.x264-LooKMaNe [PublicHD]\n &lt;a href=&quot;\nhttp://www.imdb.com/title/tt2173024/&quot; rel=&quot;nofollow&quot; target=&quot;_NEW&quot;&gt;\nhttp://www.imdb.com/title/tt2173024/&lt;/a&gt;\n\nDuration..............: 1h 49mn\nVideo.................: X264 @ 8.2 mbps (1920x816)\nFPS...................: 23.976\nAudio.................: Korean DTS 5.1 Ch 1510 kbps\nSubs..................: English Korean\n","torrent":{"xt":"urn:btih:a9a11254624313a59c36b304867cb08762c7e529","amp;dn":"Deranged.2012.1080p.BluRay.DTS.x264-LooKMaNe+%5BPublicHD%5D","amp;tr":["udp%3A%2F%2Ftracker.openbittorrent.com%3A80","udp%3A%2F%2Fopen.demonii.com%3A1337","udp%3A%2F%2Ftracker.coppersurfer.tk%3A6969","udp%3A%2F%2Fexodus.desync.com%3A6969"],"infoHash":"a9a11254624313a59c36b304867cb08762c7e529","infoHashBuffer":{"type":"Buffer","data":[169,161,18,84,98,67,19,165,156,54,179,4,134,124,176,135,98,199,229,41]},"announce":[],"urlList":[]}}