{"title":"hawaii.wmv","uid":8213956,"size":100699244,"categoryP":"porn","categoryS":"movie_clips","magnet":"?xt=urn:btih:abf29c88d8958bb35e73c53bd17bb00294c648fa&amp;dn=hawaii.wmv&amp;tr=udp%3A%2F%2Ftracker.openbittorrent.com%3A80&amp;tr=udp%3A%2F%2Fopen.demonii.com%3A1337&amp;tr=udp%3A%2F%2Ftracker.coppersurfer.tk%3A6969&amp;tr=udp%3A%2F%2Fexodus.desync.com%3A6969","seeders":0,"leechers":0,"uploader":null,"files":1,"time":1362301416,"description":"","torrent":{"xt":"urn:btih:abf29c88d8958bb35e73c53bd17bb00294c648fa","amp;dn":"hawaii.wmv","amp;tr":["udp%3A%2F%2Ftracker.openbittorrent.com%3A80","udp%3A%2F%2Fopen.demonii.com%3A1337","udp%3A%2F%2Ftracker.coppersurfer.tk%3A6969","udp%3A%2F%2Fexodus.desync.com%3A6969"],"infoHash":"abf29c88d8958bb35e73c53bd17bb00294c648fa","infoHashBuffer":{"type":"Buffer","data":[171,242,156,136,216,149,139,179,94,115,197,59,209,123,176,2,148,198,72,250]},"announce":[],"urlList":[]}}