{"title":"Holy Fuck It's Huge 3 [Split Scenes]","uid":7859426,"size":1409895630,"categoryP":"porn","categoryS":"movies","magnet":"?xt=urn:btih:aca5a9cb96b2541bbf8f2caa9e2ee9d6b761bbdd&amp;dn=Holy+Fuck+It%27s+Huge+3+%5BSplit+Scenes%5D&amp;tr=udp%3A%2F%2Ftracker.openbittorrent.com%3A80&amp;tr=udp%3A%2F%2Fopen.demonii.com%3A1337&amp;tr=udp%3A%2F%2Ftracker.coppersurfer.tk%3A6969&amp;tr=udp%3A%2F%2Fexodus.desync.com%3A6969","seeders":0,"leechers":2,"uploader":"R0thschild","files":6,"time":1353879248,"description":"Gallery: \n &lt;a href=&quot;\nhttp://imagedomino.com/?g=313394&quot; rel=&quot;nofollow&quot; target=&quot;_NEW&quot;&gt;\nhttp://imagedomino.com/?g=313394&lt;/a&gt;\n\nDirector: Juan Cuba\nStudio: Candy Shop\n\nBig black cocks and tiny white girls, this series knows just what guys like you want to see!","torrent":{"xt":"urn:btih:aca5a9cb96b2541bbf8f2caa9e2ee9d6b761bbdd","amp;dn":"Holy+Fuck+It%27s+Huge+3+%5BSplit+Scenes%5D","amp;tr":["udp%3A%2F%2Ftracker.openbittorrent.com%3A80","udp%3A%2F%2Fopen.demonii.com%3A1337","udp%3A%2F%2Ftracker.coppersurfer.tk%3A6969","udp%3A%2F%2Fexodus.desync.com%3A6969"],"infoHash":"aca5a9cb96b2541bbf8f2caa9e2ee9d6b761bbdd","infoHashBuffer":{"type":"Buffer","data":[172,165,169,203,150,178,84,27,191,143,44,170,158,46,233,214,183,97,187,221]},"announce":[],"urlList":[]}}