{"title":"ATK Galleria Premium - Elle Alexandra ell026 - 2 - 1025 pics in ","uid":8034183,"size":782469093,"categoryP":"porn","categoryS":"pictures","magnet":"?xt=urn:btih:b7cc9bf8bd9a7e07f4fdf21b1038aad06d0352a5&amp;dn=ATK+Galleria+Premium+-+Elle+Alexandra+ell026+-+2+-+1025+pics+in+&amp;tr=udp%3A%2F%2Ftracker.openbittorrent.com%3A80&amp;tr=udp%3A%2F%2Fopen.demonii.com%3A1337&amp;tr=udp%3A%2F%2Ftracker.coppersurfer.tk%3A6969&amp;tr=udp%3A%2F%2Fexodus.desync.com%3A6969","seeders":0,"leechers":1,"uploader":"bestec1234","files":-1,"time":1358484931,"description":" &lt;a href=&quot;http://bayimg.com/tag/ell026/&quot; rel=&quot;nofollow&quot; target=&quot;_NEW&quot;&gt;http://bayimg.com/tag/ell026/&lt;/a&gt;\n\nTo see the previews, you may have to check 'No I don't mind offensive material' under 'Settings' on bayimg.","torrent":{"xt":"urn:btih:b7cc9bf8bd9a7e07f4fdf21b1038aad06d0352a5","amp;dn":"ATK+Galleria+Premium+-+Elle+Alexandra+ell026+-+2+-+1025+pics+in+","amp;tr":["udp%3A%2F%2Ftracker.openbittorrent.com%3A80","udp%3A%2F%2Fopen.demonii.com%3A1337","udp%3A%2F%2Ftracker.coppersurfer.tk%3A6969","udp%3A%2F%2Fexodus.desync.com%3A6969"],"infoHash":"b7cc9bf8bd9a7e07f4fdf21b1038aad06d0352a5","infoHashBuffer":{"type":"Buffer","data":[183,204,155,248,189,154,126,7,244,253,242,27,16,56,170,208,109,3,82,165]},"announce":[],"urlList":[]}}