{"title":"Anissa Kate - Inspector Anal, Scene 4 (EvilAngel) HD","uid":8069057,"size":1238584365,"categoryP":"porn","categoryS":"hd___movies","magnet":"?xt=urn:btih:bf6e43a0a9e88f18b67a9d9f8788c08773d924be&amp;dn=Anissa+Kate+-+Inspector+Anal%2C+Scene+4+%28EvilAngel%29+HD&amp;tr=udp%3A%2F%2Ftracker.openbittorrent.com%3A80&amp;tr=udp%3A%2F%2Fopen.demonii.com%3A1337&amp;tr=udp%3A%2F%2Ftracker.coppersurfer.tk%3A6969&amp;tr=udp%3A%2F%2Fexodus.desync.com%3A6969","seeders":0,"leechers":1,"uploader":"R0thschild","files":1,"time":1359233434,"description":"Gallery: \n &lt;a href=&quot;\nhttp://hqpdb.com/viewtopic.php?f=12&amp;t=12816&quot; rel=&quot;nofollow&quot; target=&quot;_NEW&quot;&gt;\nhttp://hqpdb.com/viewtopic.php?f=12&amp;t=12816&lt;/a&gt;\n\n------------------------------------------\n         My torrents at thePiratebay\n------------------------------------------\n  &lt;a href=&quot;\nhttp://thepiratebay.se/user/R0thschild/&quot; rel=&quot;nofollow&quot; target=&quot;_NEW&quot;&gt;\nhttp://thepiratebay.se/user/R0thschild/&lt;/a&gt;\t","torrent":{"xt":"urn:btih:bf6e43a0a9e88f18b67a9d9f8788c08773d924be","amp;dn":"Anissa+Kate+-+Inspector+Anal%2C+Scene+4+%28EvilAngel%29+HD","amp;tr":["udp%3A%2F%2Ftracker.openbittorrent.com%3A80","udp%3A%2F%2Fopen.demonii.com%3A1337","udp%3A%2F%2Ftracker.coppersurfer.tk%3A6969","udp%3A%2F%2Fexodus.desync.com%3A6969"],"infoHash":"bf6e43a0a9e88f18b67a9d9f8788c08773d924be","infoHashBuffer":{"type":"Buffer","data":[191,110,67,160,169,232,143,24,182,122,157,159,135,136,192,135,115,217,36,190]},"announce":[],"urlList":[]}}