{"title":"Nubiles.13.01.15.Linda.Lay.Naughty.Girl.Shower.XXX.720p.WMV-KTR","uid":8053151,"size":356905151,"categoryP":"porn","categoryS":"movie_clips","magnet":"?xt=urn:btih:c1c18b3922d2b1eb8833df5c50847551b6281578&amp;dn=Nubiles.13.01.15.Linda.Lay.Naughty.Girl.Shower.XXX.720p.WMV-KTR+&amp;tr=udp%3A%2F%2Ftracker.openbittorrent.com%3A80&amp;tr=udp%3A%2F%2Fopen.demonii.com%3A1337&amp;tr=udp%3A%2F%2Ftracker.coppersurfer.tk%3A6969&amp;tr=udp%3A%2F%2Fexodus.desync.com%3A6969","seeders":0,"leechers":0,"uploader":"R0thschild","files":2,"time":1358897406,"description":"Gallery: \n &lt;a href=&quot;\nhttp://hqpdb.com/viewtopic.php?f=43&amp;t=11563&quot; rel=&quot;nofollow&quot; target=&quot;_NEW&quot;&gt;\nhttp://hqpdb.com/viewtopic.php?f=43&amp;t=11563&lt;/a&gt;","torrent":{"xt":"urn:btih:c1c18b3922d2b1eb8833df5c50847551b6281578","amp;dn":"Nubiles.13.01.15.Linda.Lay.Naughty.Girl.Shower.XXX.720p.WMV-KTR+","amp;tr":["udp%3A%2F%2Ftracker.openbittorrent.com%3A80","udp%3A%2F%2Fopen.demonii.com%3A1337","udp%3A%2F%2Ftracker.coppersurfer.tk%3A6969","udp%3A%2F%2Fexodus.desync.com%3A6969"],"infoHash":"c1c18b3922d2b1eb8833df5c50847551b6281578","infoHashBuffer":{"type":"Buffer","data":[193,193,139,57,34,210,177,235,136,51,223,92,80,132,117,81,182,40,21,120]},"announce":[],"urlList":[]}}