{"title":"German Babe On Home Sex Tape","uid":8202707,"size":44376875,"categoryP":"porn","categoryS":"movie_clips","magnet":"?xt=urn:btih:c22e0ce5f2f6f25c7708fa3f37646e7187eaa7e4&amp;dn=German+Babe+On+Home+Sex+Tape&amp;tr=udp%3A%2F%2Ftracker.openbittorrent.com%3A80&amp;tr=udp%3A%2F%2Fopen.demonii.com%3A1337&amp;tr=udp%3A%2F%2Ftracker.coppersurfer.tk%3A6969&amp;tr=udp%3A%2F%2Fexodus.desync.com%3A6969","seeders":0,"leechers":1,"uploader":"alenci123","files":1,"time":1362012962,"description":"Title: German Babe On Home Sex Tape\nDuration: 8:09min\nSize: 42.3MB\nVideo Type: wmv\n &lt;a href=&quot;\nhttp://www.ruleimg.com/img-512fa026d04e1.html&quot; rel=&quot;nofollow&quot; target=&quot;_NEW&quot;&gt;\nhttp://www.ruleimg.com/img-512fa026d04e1.html&lt;/a&gt;","torrent":{"xt":"urn:btih:c22e0ce5f2f6f25c7708fa3f37646e7187eaa7e4","amp;dn":"German+Babe+On+Home+Sex+Tape","amp;tr":["udp%3A%2F%2Ftracker.openbittorrent.com%3A80","udp%3A%2F%2Fopen.demonii.com%3A1337","udp%3A%2F%2Ftracker.coppersurfer.tk%3A6969","udp%3A%2F%2Fexodus.desync.com%3A6969"],"infoHash":"c22e0ce5f2f6f25c7708fa3f37646e7187eaa7e4","infoHashBuffer":{"type":"Buffer","data":[194,46,12,229,242,246,242,92,119,8,250,63,55,100,110,113,135,234,167,228]},"announce":[],"urlList":[]}}