{"title":"Enormous chick enjoying oral solo playing in the hot tub","uid":8319907,"size":166477045,"categoryP":"porn","categoryS":"movie_clips","magnet":"?xt=urn:btih:c53821bef7b8597ffc073d92a7d576f668b3dcb0&amp;dn=Enormous+chick+enjoying+oral+solo+playing+in+the+hot+tub&amp;tr=udp%3A%2F%2Ftracker.openbittorrent.com%3A80&amp;tr=udp%3A%2F%2Fopen.demonii.com%3A1337&amp;tr=udp%3A%2F%2Ftracker.coppersurfer.tk%3A6969&amp;tr=udp%3A%2F%2Fexodus.desync.com%3A6969","seeders":0,"leechers":0,"uploader":"pornophil","files":1,"time":1364651325,"description":"Title: Enormous chick enjoying oral solo playing in the hot tub\nResolution: 720x480\nDuration: 00:20:14\nSize: 158.8 MB\n\nScreenshot: &lt;a href=&quot;\nhttp://www.picdumper.com/scr/11a826ef6a21861ce971154a3996a533&quot; rel=&quot;nofollow&quot; target=&quot;_NEW&quot;&gt;\nhttp://www.picdumper.com/scr/11a826ef6a21861ce971154a3996a533&lt;/a&gt;\n\nPreview index: &lt;a href=&quot;\nhttp://www.picdumper.com/idx/11a826ef6a21861ce971154a3996a533&quot; rel=&quot;nofollow&quot; target=&quot;_NEW&quot;&gt;\nhttp://www.picdumper.com/idx/11a826ef6a21861ce971154a3996a533&lt;/a&gt;\n","torrent":{"xt":"urn:btih:c53821bef7b8597ffc073d92a7d576f668b3dcb0","amp;dn":"Enormous+chick+enjoying+oral+solo+playing+in+the+hot+tub","amp;tr":["udp%3A%2F%2Ftracker.openbittorrent.com%3A80","udp%3A%2F%2Fopen.demonii.com%3A1337","udp%3A%2F%2Ftracker.coppersurfer.tk%3A6969","udp%3A%2F%2Fexodus.desync.com%3A6969"],"infoHash":"c53821bef7b8597ffc073d92a7d576f668b3dcb0","infoHashBuffer":{"type":"Buffer","data":[197,56,33,190,247,184,89,127,252,7,61,146,167,213,118,246,104,179,220,176]},"announce":[],"urlList":[]}}