{"title":"Dave's Old Porn S02E06 Lisa Lampanelli, Herschel Savage, Ron Jer","uid":8001991,"size":343946378,"categoryP":"video","categoryS":"tv_shows","magnet":"?xt=urn:btih:c924ae39c783ae290a3d63e9e066ba2da44b38c4&amp;dn=Dave%27s+Old+Porn+S02E06+Lisa+Lampanelli%2C+Herschel+Savage%2C+Ron+Jer&amp;tr=udp%3A%2F%2Ftracker.openbittorrent.com%3A80&amp;tr=udp%3A%2F%2Fopen.demonii.com%3A1337&amp;tr=udp%3A%2F%2Ftracker.coppersurfer.tk%3A6969&amp;tr=udp%3A%2F%2Fexodus.desync.com%3A6969","seeders":0,"leechers":2,"uploader":"Crim2k8","files":1,"time":1357793538,"description":"Dave's Old Porn S02E06 Lisa Lampanelli, Herschel Savage, Ron Jeremy\n\n\nDownloaded from alt.binaries.hdtv newsgroup\n\nConverted by me from 1080i HDTV .ts file\n\n\nPlease rate and comment. It's imortant for other fans to recognize that this isn't one of the fakes roaming around.\n\nThanks.\n\n\nOh, and to the person who was rude to TV Team for not having Eps 6 and 7 - Go fuck yourself. TV Team work damned hard, and I don't see you adding anything constructive in the way of torrents. Quit being such an entitled little spoiled brat and show some appreciation for everything they do.","torrent":{"xt":"urn:btih:c924ae39c783ae290a3d63e9e066ba2da44b38c4","amp;dn":"Dave%27s+Old+Porn+S02E06+Lisa+Lampanelli%2C+Herschel+Savage%2C+Ron+Jer","amp;tr":["udp%3A%2F%2Ftracker.openbittorrent.com%3A80","udp%3A%2F%2Fopen.demonii.com%3A1337","udp%3A%2F%2Ftracker.coppersurfer.tk%3A6969","udp%3A%2F%2Fexodus.desync.com%3A6969"],"infoHash":"c924ae39c783ae290a3d63e9e066ba2da44b38c4","infoHashBuffer":{"type":"Buffer","data":[201,36,174,57,199,131,174,41,10,61,99,233,224,102,186,45,164,75,56,196]},"announce":[],"urlList":[]}}