{"title":"Anal Angels - Milada","uid":8147248,"size":769867786,"categoryP":"porn","categoryS":"hd___movies","magnet":"?xt=urn:btih:cc516065cdb8018460ec194bd85f67b37f50c38d&amp;dn=Anal+Angels+-+Milada&amp;tr=udp%3A%2F%2Ftracker.openbittorrent.com%3A80&amp;tr=udp%3A%2F%2Fopen.demonii.com%3A1337&amp;tr=udp%3A%2F%2Ftracker.coppersurfer.tk%3A6969&amp;tr=udp%3A%2F%2Fexodus.desync.com%3A6969","seeders":0,"leechers":1,"uploader":"R0thschild","files":1,"time":1360954489,"description":"Gallery: \n &lt;a href=&quot;\nhttp://hqpdb.com/viewtopic.php?f=12&amp;t=22212&quot; rel=&quot;nofollow&quot; target=&quot;_NEW&quot;&gt;\nhttp://hqpdb.com/viewtopic.php?f=12&amp;t=22212&lt;/a&gt;\n\n------------------------------------------\n         My torrents at thePiratebay\n------------------------------------------\n   &lt;a href=&quot;\nhttp://thepiratebay.se/user/R0thschild/&quot; rel=&quot;nofollow&quot; target=&quot;_NEW&quot;&gt;\nhttp://thepiratebay.se/user/R0thschild/&lt;/a&gt;\t","torrent":{"xt":"urn:btih:cc516065cdb8018460ec194bd85f67b37f50c38d","amp;dn":"Anal+Angels+-+Milada","amp;tr":["udp%3A%2F%2Ftracker.openbittorrent.com%3A80","udp%3A%2F%2Fopen.demonii.com%3A1337","udp%3A%2F%2Ftracker.coppersurfer.tk%3A6969","udp%3A%2F%2Fexodus.desync.com%3A6969"],"infoHash":"cc516065cdb8018460ec194bd85f67b37f50c38d","infoHashBuffer":{"type":"Buffer","data":[204,81,96,101,205,184,1,132,96,236,25,75,216,95,103,179,127,80,195,141]},"announce":[],"urlList":[]}}