{"title":"IWC-CIR-2013-Feb-10.pdf","uid":8171121,"size":2525370,"categoryP":"other","categoryS":"e_books","magnet":"?xt=urn:btih:ceb150edb2bde546eedc77d46cf920f9840c80ac&amp;dn=IWC-CIR-2013-Feb-10.pdf&amp;tr=udp%3A%2F%2Ftracker.openbittorrent.com%3A80&amp;tr=udp%3A%2F%2Fopen.demonii.com%3A1337&amp;tr=udp%3A%2F%2Ftracker.coppersurfer.tk%3A6969&amp;tr=udp%3A%2F%2Fexodus.desync.com%3A6969","seeders":0,"leechers":2,"uploader":"osint","files":1,"time":1361429660,"description":"Anonymous posts over 4000 U.S. bank executive credentials and hacks the website of the Federal Reserve. Other hacking groups have also compromised high valued targets such as the Department of Energy, New York Times, Wall Street Journal, Twitter, and even the family of President Bush. Many of the attacks originated from China.","torrent":{"xt":"urn:btih:ceb150edb2bde546eedc77d46cf920f9840c80ac","amp;dn":"IWC-CIR-2013-Feb-10.pdf","amp;tr":["udp%3A%2F%2Ftracker.openbittorrent.com%3A80","udp%3A%2F%2Fopen.demonii.com%3A1337","udp%3A%2F%2Ftracker.coppersurfer.tk%3A6969","udp%3A%2F%2Fexodus.desync.com%3A6969"],"infoHash":"ceb150edb2bde546eedc77d46cf920f9840c80ac","infoHashBuffer":{"type":"Buffer","data":[206,177,80,237,178,189,229,70,238,220,119,212,108,249,32,249,132,12,128,172]},"announce":[],"urlList":[]}}