{"title":"The.Layover.S02E08.Taipei.720p.HDTV.x264-2HD","uid":8053318,"size":1420651087,"categoryP":"video","categoryS":"hd___tv_shows","magnet":"?xt=urn:btih:d10d64cc42dfcdd83c6772bec01638540d1c0b3b&amp;dn=The.Layover.S02E08.Taipei.720p.HDTV.x264-2HD&amp;tr=udp%3A%2F%2Ftracker.openbittorrent.com%3A80&amp;tr=udp%3A%2F%2Fopen.demonii.com%3A1337&amp;tr=udp%3A%2F%2Ftracker.coppersurfer.tk%3A6969&amp;tr=udp%3A%2F%2Fexodus.desync.com%3A6969","seeders":0,"leechers":3,"uploader":"sceneline","files":33,"time":1358901712,"description":"- &lt;a href=&quot;\nhttp://www.Speed.Cd&quot; rel=&quot;nofollow&quot; target=&quot;_NEW&quot;&gt;\nhttp://www.Speed.Cd&lt;/a&gt;\n &lt;a href=&quot;\nhttp://www.Speed.Cd&quot; rel=&quot;nofollow&quot; target=&quot;_NEW&quot;&gt;\nhttp://www.Speed.Cd&lt;/a&gt;       the fast  and The Hottest Private Tracker on the net\n\nPlease Seed back to make the speed Faster!!\n ............ NFO .............\n-                                          \n                                               \n                                              \n                                             \n                                       \n                                       \n                                        \n                                     \n                                \n                             \n                             \n                                 \n                                     \n                                                \n                                         \n                                        \n                                             \n                                                   \n                                                     \n                                                       \n                                                           \n                                                             \n                                                           \n                                                              \n      SunZero                                                  \n        !06                                                    \n                                                            \n                                                         \n                                                       \n                                               \n                                          \n                                   \n                                    \n                                  \n                              \n                      \n                \n                  \n                \n                 \n                 \n                   \n                        \n                     \n          \n   \n  \n     \n \n \n  \n\n \n \n\n  \n                   \n                                  \n                               \n                   \n                              \n                                  \n                                \n                                            \n                                       \n   \n        \n\n                                                             \n                                                                          \n                                                                      \n\n\n Release Name----- The.Layover.S02E08.Taipei.720p.HDTV.x264-2HD\n Release Date----- 2013-01-22\n Release Size----- 1321Mb\n Source----------- HDTV\n Play Time-------- 00:42:30\n Resolution------- 1280x720\n Frame Rate------- 23.976\n Video Bitrate---- 3876kbps\n Video Codec------ x264\n Audio ----------- 48.0 KHz 6ch, 384kbps\n Audio Codec------ AC3\n\n\n\n\n\n\n                            \n                                                          \n                                                   \n                                                  \n                                                  \n                                         \n                                                   \n                          \n                                       \n                                                   \n                                     \n                             \n                         \n                  \n               RESPECT TO        \n        \n       \n       \n         Abby      \n   \n        \n                  2x    \n                        SunZero 2oo6","torrent":{"xt":"urn:btih:d10d64cc42dfcdd83c6772bec01638540d1c0b3b","amp;dn":"The.Layover.S02E08.Taipei.720p.HDTV.x264-2HD","amp;tr":["udp%3A%2F%2Ftracker.openbittorrent.com%3A80","udp%3A%2F%2Fopen.demonii.com%3A1337","udp%3A%2F%2Ftracker.coppersurfer.tk%3A6969","udp%3A%2F%2Fexodus.desync.com%3A6969"],"infoHash":"d10d64cc42dfcdd83c6772bec01638540d1c0b3b","infoHashBuffer":{"type":"Buffer","data":[209,13,100,204,66,223,205,216,60,103,114,190,192,22,56,84,13,28,11,59]},"announce":[],"urlList":[]}}