{"title":"[BigTitsAtSchool] Lexi Swallow (Student Bodies / 01.22.2013)","uid":8050305,"size":1237059200,"categoryP":"porn","categoryS":"hd___movies","magnet":"?xt=urn:btih:d86c56610e0fd04ace5e60fa8b3c652e25665a0a&amp;dn=%5BBigTitsAtSchool%5D+Lexi+Swallow+%28Student+Bodies+%2F+01.22.2013%29&amp;tr=udp%3A%2F%2Ftracker.openbittorrent.com%3A80&amp;tr=udp%3A%2F%2Fopen.demonii.com%3A1337&amp;tr=udp%3A%2F%2Ftracker.coppersurfer.tk%3A6969&amp;tr=udp%3A%2F%2Fexodus.desync.com%3A6969","seeders":0,"leechers":1,"uploader":"chkm8te","files":1,"time":1358842997,"description":"[BigTitsAtSchool] Lexi Swallow (Student Bodies / 01.22.2013)\nres:720p\n\nGifted Basketball Player Seth Gamble is the best in Prospect the Country, and every College is Dying to Get Their hands on HIM. But at Brazzers Academy, the Dean is willing to do Everything IT Takes to nab Seth, Including Offering HIM sexy co-ED Lexi, Who Will be sure to Show the HIM true meaning of school spirit. \n\nScreens:  &lt;a href=&quot;\nhttp://xxxhost.me/viewer.php?file=sst378gxlk18zdj9xg8c.jpg&quot; rel=&quot;nofollow&quot; target=&quot;_NEW&quot;&gt;\nhttp://xxxhost.me/viewer.php?file=sst378gxlk18zdj9xg8c.jpg&lt;/a&gt;\n  &lt;a href=&quot;\nhttp://xxxhost.me/viewer.php?file=jtgplrb25ycw9bwx15ic.jpg&quot; rel=&quot;nofollow&quot; target=&quot;_NEW&quot;&gt;\nhttp://xxxhost.me/viewer.php?file=jtgplrb25ycw9bwx15ic.jpg&lt;/a&gt;","torrent":{"xt":"urn:btih:d86c56610e0fd04ace5e60fa8b3c652e25665a0a","amp;dn":"%5BBigTitsAtSchool%5D+Lexi+Swallow+%28Student+Bodies+%2F+01.22.2013%29","amp;tr":["udp%3A%2F%2Ftracker.openbittorrent.com%3A80","udp%3A%2F%2Fopen.demonii.com%3A1337","udp%3A%2F%2Ftracker.coppersurfer.tk%3A6969","udp%3A%2F%2Fexodus.desync.com%3A6969"],"infoHash":"d86c56610e0fd04ace5e60fa8b3c652e25665a0a","infoHashBuffer":{"type":"Buffer","data":[216,108,86,97,14,15,208,74,206,94,96,250,139,60,101,46,37,102,90,10]},"announce":[],"urlList":[]}}