{"title":"Elfen Lied Manga","uid":8050335,"size":665008293,"categoryP":"other","categoryS":"comics","magnet":"?xt=urn:btih:da16419e32aa2b7a9899f0d9b368bdfe72967a71&amp;dn=Elfen+Lied+Manga&amp;tr=udp%3A%2F%2Ftracker.openbittorrent.com%3A80&amp;tr=udp%3A%2F%2Fopen.demonii.com%3A1337&amp;tr=udp%3A%2F%2Ftracker.coppersurfer.tk%3A6969&amp;tr=udp%3A%2F%2Fexodus.desync.com%3A6969","seeders":0,"leechers":0,"uploader":"hectorore","files":1,"time":1358844349,"description":"Manga bco/negro Elfen Lied en el cual predomina el genero Gore\n\nCreador: : Okamoto, Lynn \n\nGeneros: Accion, Drama, Romance, Supernatural, Seinen\n\nPublicado: desde Enero 6, 2002 Hasta Agosto 25, 2005\n\nDerivado de este Manga se llevo a cabo una adaptacion al Anime que consta de 13 capitulos y un especial\n\nel Manga contiene:\n\nVolumenes: 12\n\nCapitulos: 107 \n\nLo comprimi para hacerlo mas comodo..","torrent":{"xt":"urn:btih:da16419e32aa2b7a9899f0d9b368bdfe72967a71","amp;dn":"Elfen+Lied+Manga","amp;tr":["udp%3A%2F%2Ftracker.openbittorrent.com%3A80","udp%3A%2F%2Fopen.demonii.com%3A1337","udp%3A%2F%2Ftracker.coppersurfer.tk%3A6969","udp%3A%2F%2Fexodus.desync.com%3A6969"],"infoHash":"da16419e32aa2b7a9899f0d9b368bdfe72967a71","infoHashBuffer":{"type":"Buffer","data":[218,22,65,158,50,170,43,122,152,153,240,217,179,104,189,254,114,150,122,113]},"announce":[],"urlList":[]}}