{"title":"Ballad of Serenity (Firefly theme)","uid":8152315,"size":1824042,"categoryP":"audio","categoryS":"music","magnet":"?xt=urn:btih:dc936cf5f675a45be887355184f8b301eb322e71&amp;dn=Ballad+of+Serenity+%28Firefly+theme%29&amp;tr=udp%3A%2F%2Ftracker.openbittorrent.com%3A80&amp;tr=udp%3A%2F%2Fopen.demonii.com%3A1337&amp;tr=udp%3A%2F%2Ftracker.coppersurfer.tk%3A6969&amp;tr=udp%3A%2F%2Fexodus.desync.com%3A6969","seeders":0,"leechers":1,"uploader":"digitalevil","files":1,"time":1361076549,"description":"I couldn't find this torrent any where, so I guess I will upload it. Enjoy. :)","torrent":{"xt":"urn:btih:dc936cf5f675a45be887355184f8b301eb322e71","amp;dn":"Ballad+of+Serenity+%28Firefly+theme%29","amp;tr":["udp%3A%2F%2Ftracker.openbittorrent.com%3A80","udp%3A%2F%2Fopen.demonii.com%3A1337","udp%3A%2F%2Ftracker.coppersurfer.tk%3A6969","udp%3A%2F%2Fexodus.desync.com%3A6969"],"infoHash":"dc936cf5f675a45be887355184f8b301eb322e71","infoHashBuffer":{"type":"Buffer","data":[220,147,108,245,246,117,164,91,232,135,53,81,132,248,179,1,235,50,46,113]},"announce":[],"urlList":[]}}