{"title":"Billig Willig - Cheap And Horny","uid":8226296,"size":1042438144,"categoryP":"porn","categoryS":"movies","magnet":"?xt=urn:btih:f81523bc91420b76489117a851dd83d5017243aa&amp;dn=Billig+Willig+-+Cheap+And+Horny&amp;tr=udp%3A%2F%2Ftracker.openbittorrent.com%3A80&amp;tr=udp%3A%2F%2Fopen.demonii.com%3A1337&amp;tr=udp%3A%2F%2Ftracker.coppersurfer.tk%3A6969&amp;tr=udp%3A%2F%2Fexodus.desync.com%3A6969","seeders":0,"leechers":1,"uploader":"irealu69","files":-1,"time":1362605849,"description":"Billig Willig - Cheap And Horny\n~~~~~~~~~~~~~~~~~~~~~~~~~~~~~~~\n\nScreenshots:\n~~~~~~~~~~~~\n &lt;a href=&quot;\nhttp://picturevip.com/x/clean/ItY&quot; rel=&quot;nofollow&quot; target=&quot;_NEW&quot;&gt;\nhttp://picturevip.com/x/clean/ItY&lt;/a&gt;\n &lt;a href=&quot;\nhttp://picturevip.com/x/clean/Itl&quot; rel=&quot;nofollow&quot; target=&quot;_NEW&quot;&gt;\nhttp://picturevip.com/x/clean/Itl&lt;/a&gt;\n &lt;a href=&quot;\nhttp://picturevip.com/x/clean/Its&quot; rel=&quot;nofollow&quot; target=&quot;_NEW&quot;&gt;\nhttp://picturevip.com/x/clean/Its&lt;/a&gt;\n &lt;a href=&quot;\nhttp://picturevip.com/x/clean/Itz&quot; rel=&quot;nofollow&quot; target=&quot;_NEW&quot;&gt;\nhttp://picturevip.com/x/clean/Itz&lt;/a&gt;\n &lt;a href=&quot;\nhttp://picturevip.com/x/clean/ItS&quot; rel=&quot;nofollow&quot; target=&quot;_NEW&quot;&gt;\nhttp://picturevip.com/x/clean/ItS&lt;/a&gt;\n\n\nVideos Info:\n~~~~~~~~~~~~\nSize: 994.15 MB\nResolution: 352x288","torrent":{"xt":"urn:btih:f81523bc91420b76489117a851dd83d5017243aa","amp;dn":"Billig+Willig+-+Cheap+And+Horny","amp;tr":["udp%3A%2F%2Ftracker.openbittorrent.com%3A80","udp%3A%2F%2Fopen.demonii.com%3A1337","udp%3A%2F%2Ftracker.coppersurfer.tk%3A6969","udp%3A%2F%2Fexodus.desync.com%3A6969"],"infoHash":"f81523bc91420b76489117a851dd83d5017243aa","infoHashBuffer":{"type":"Buffer","data":[248,21,35,188,145,66,11,118,72,145,23,168,81,221,131,213,1,114,67,170]},"announce":[],"urlList":[]}}