{"title":"WickedLive.10.01.15.Miko.Sinz.And.Asa.Akira.XXX.720p.MP4-KTR","uid":7992338,"size":1539027877,"categoryP":"porn","categoryS":"other","magnet":"?xt=urn:btih:fc5e747ad4509c5d19112137bd8556f343987b90&amp;dn=WickedLive.10.01.15.Miko.Sinz.And.Asa.Akira.XXX.720p.MP4-KTR&amp;tr=udp%3A%2F%2Ftracker.openbittorrent.com%3A80&amp;tr=udp%3A%2F%2Fopen.demonii.com%3A1337&amp;tr=udp%3A%2F%2Ftracker.coppersurfer.tk%3A6969&amp;tr=udp%3A%2F%2Fexodus.desync.com%3A6969","seeders":0,"leechers":1,"uploader":"R0thschild","files":2,"time":1357471916,"description":"Gallery: \n &lt;a href=&quot;\nhttp://hqpdb.com/viewtopic.php?f=42&amp;t=6012&quot; rel=&quot;nofollow&quot; target=&quot;_NEW&quot;&gt;\nhttp://hqpdb.com/viewtopic.php?f=42&amp;t=6012&lt;/a&gt;","torrent":{"xt":"urn:btih:fc5e747ad4509c5d19112137bd8556f343987b90","amp;dn":"WickedLive.10.01.15.Miko.Sinz.And.Asa.Akira.XXX.720p.MP4-KTR","amp;tr":["udp%3A%2F%2Ftracker.openbittorrent.com%3A80","udp%3A%2F%2Fopen.demonii.com%3A1337","udp%3A%2F%2Ftracker.coppersurfer.tk%3A6969","udp%3A%2F%2Fexodus.desync.com%3A6969"],"infoHash":"fc5e747ad4509c5d19112137bd8556f343987b90","infoHashBuffer":{"type":"Buffer","data":[252,94,116,122,212,80,156,93,25,17,33,55,189,133,86,243,67,152,123,144]},"announce":[],"urlList":[]}}